magnet/__init__.py
magnet/builder/__init__.py
magnet/builder/unet.py
magnet/builder/unetr.py
magnet/data/__init__.py
magnet/data/targeting.py
magnet/losses/__init__.py
magnet/losses/distillation.py
magnet/losses/protocols.py
magnet/losses/targeting.py
magnet/managers/__init__.py
magnet/managers/monai.py
magnet/managers/protocols.py
magnet/managers/targeting.py
magnet/networks/__init__.py
magnet/networks/hemis.py
magnet/networks/unet/__init__.py
magnet/networks/unet/decoders.py
magnet/networks/unet/encoders.py
magnet/networks/unet/unet.py
magnet/networks/unetr/__init__.py
magnet/networks/unetr/decoders.py
magnet/networks/unetr/encoders.py
magnet/networks/unetr/multimodality.py
magnet/nn/__init__.py
magnet/nn/fusion/__init__.py
magnet/nn/fusion/fuse.py
magnet/nn/shared.py
magnet/version.py
magms-2.2.dist-info/LICENSE
magms-2.2.dist-info/METADATA
magms-2.2.dist-info/WHEEL
magms-2.2.dist-info/RECORD
