Metadata-Version: 2.1
Name: magms
Version: 2.2
Summary: Modality-Agnostic Learning for Medical Image Segmentation Using Multi-modality Self-distillation (v2.2)
Home-page: https://github.com/kisonho/magnet.git
Author: Qisheng He
Author-email: Qisheng.He@wayne.edu
Requires-Python: >=3.9,<4.0
Classifier: Programming Language :: Python :: 3
Classifier: Programming Language :: Python :: 3.9
Classifier: Programming Language :: Python :: 3.10
Classifier: Programming Language :: Python :: 3.11
Classifier: Programming Language :: Python :: 3.12
Requires-Dist: torch
Requires-Dist: torchmanager (>=1.1,<2.0)
Project-URL: Repository, https://github.com/kisonho/magnet.git
